fmu/__init__.py
fmu/config/__init__.py
fmu/config/_configparserfmu_ipl.py
fmu/config/_loader.py
fmu/config/_oyaml.py
fmu/config/configparserfmu.py
fmu/config/etc.py
fmu/config/fmuconfigrunner.py
fmu/config/py.typed
fmu/config/utilities.py
fmu/config/version.py
fmu_config-1.6.0.dist-info/licenses/LICENSE
fmu_config-1.6.0.dist-info/METADATA
fmu_config-1.6.0.dist-info/WHEEL
fmu_config-1.6.0.dist-info/entry_points.txt
fmu_config-1.6.0.dist-info/top_level.txt
fmu_config-1.6.0.dist-info/RECORD
