Metadata-Version: 2.4
Name: fmu-config
Version: 1.6.0
Summary: Library for various config scripts in FMU scopes
Author-email: Equinor <jriv@equinor.com>
License:                    GNU LESSER GENERAL PUBLIC LICENSE
Project-URL: Homepage, https://github.com/equinor/fmu-config
Project-URL: Repository, https://github.com/equinor/fmu-config
Keywords: fmu,config
Classifier: Development Status :: 2 - Pre-Alpha
Classifier: Intended Audience :: Developers
Classifier: Natural Language :: English
Classifier: Programming Language :: Python :: 3
Classifier: Programming Language :: Python :: 3.11
Classifier: Programming Language :: Python :: 3.12
Classifier: Programming Language :: Python :: 3.13
Classifier: Programming Language :: Python :: 3.14
Requires-Python: >=3.11
License-File: LICENSE
Requires-Dist: pyyaml
Provides-Extra: dev
Requires-Dist: astroid; extra == "dev"
Requires-Dist: autoapi; extra == "dev"
Requires-Dist: coverage; extra == "dev"
Requires-Dist: mypy; extra == "dev"
Requires-Dist: myst-parser; extra == "dev"
Requires-Dist: pylint; extra == "dev"
Requires-Dist: pytest-runner; extra == "dev"
Requires-Dist: pytest; extra == "dev"
Requires-Dist: rstcheck; extra == "dev"
Requires-Dist: ruff; extra == "dev"
Requires-Dist: sphinx_rtd_theme; extra == "dev"
Requires-Dist: Sphinx; extra == "dev"
Requires-Dist: types-PyYAML; extra == "dev"
Dynamic: license-file
